.gitignore
CHANGES.txt
LICENSE.txt
MANIFEST.in
README.rst
setup.py
botocore_paste/__init__.py
botocore_paste.egg-info/PKG-INFO
botocore_paste.egg-info/SOURCES.txt
botocore_paste.egg-info/dependency_links.txt
botocore_paste.egg-info/not-zip-safe
botocore_paste.egg-info/requires.txt
botocore_paste.egg-info/top_level.txt
botocore_paste/tests/__init__.py
botocore_paste/tests/config_1.ini
botocore_paste/tests/credentials_1.ini
botocore_paste/tests/test_botocore_paste.py