Metadata-Version: 1.1
Name: botocore-paste
Version: 0.2
Summary: Adapt botocore to paste
Home-page: https://github.com/gjo/botocore_paste
Author: OCHIAI, Gouji
Author-email: gjo.ext@gmail.com
License: BSD
Platform: UNKNOWN
Classifier: Framework :: Paste
Classifier: Framework :: Pyramid
Classifier: License :: OSI Approved :: BSD License
Classifier: Programming Language :: Python
Classifier: Programming Language :: Python :: 2.7
Classifier: Programming Language :: Python :: 3.5
